fullask_rest_framework/__init__.py
fullask_rest_framework/cli.py
fullask_rest_framework/contrib/__init__.py
fullask_rest_framework/contrib/admin/__init__.py
fullask_rest_framework/contrib/admin/views.py
fullask_rest_framework/contrib/admin/templates/index.html
fullask_rest_framework/contrib/admin/templates/login_form.html
fullask_rest_framework/contrib/admin/templates/static/loigin_form.css
fullask_rest_framework/createproject_template/app_template/__init__.txt
fullask_rest_framework/createproject_template/app_template/models.txt
fullask_rest_framework/createproject_template/app_template/resources.txt
fullask_rest_framework/createproject_template/app_template/schemas.txt
fullask_rest_framework/createproject_template/project_template/__init__.txt
fullask_rest_framework/createproject_template/project_template/app.txt
fullask_rest_framework/createproject_template/project_template/config.py.txt
fullask_rest_framework/createproject_template/project_template/factory.txt
fullask_rest_framework/createproject_template/project_template/tests.txt
fullask_rest_framework/db/__init__.py
fullask_rest_framework/db/transaction.py
fullask_rest_framework/db/sqlalchemy/__init__.py
fullask_rest_framework/db/sqlalchemy/base_model.py
fullask_rest_framework/db/sqlalchemy/mixins.py
fullask_rest_framework/factory/__init__.py
fullask_rest_framework/factory/app_factory.py
fullask_rest_framework/factory/exceptions.py
fullask_rest_framework/factory/extensions.py
fullask_rest_framework/factory/microapp.py
fullask_rest_framework/factory/warnings.py
fullask_rest_framework/httptypes/__init__.py
fullask_rest_framework/httptypes/filtering.py
fullask_rest_framework/httptypes/pagination.py
fullask_rest_framework/httptypes/sorting.py
fullask_rest_framework/repositories/__init__.py
fullask_rest_framework/repositories/base.py
fullask_rest_framework/repositories/crud.py
fullask_rest_framework/repositories/mongodb/__init__.py
fullask_rest_framework/repositories/redis/__init__.py
fullask_rest_framework-0.7.1.dist-info/entry_points.txt
fullask_rest_framework-0.7.1.dist-info/LICENSE
fullask_rest_framework-0.7.1.dist-info/WHEEL
fullask_rest_framework-0.7.1.dist-info/METADATA
fullask_rest_framework-0.7.1.dist-info/RECORD
