Metadata-Version: 2.1
Name: fullask-rest-framework
Version: 0.7.1
Summary: A fully-supported flask extension to build REST API.
Author-email: tgoddessana <twicegoddessana1229@gmail.com>
Requires-Python: >=3.9
Classifier: Development Status :: 2 - Pre-Alpha
Classifier: Intended Audience :: Developers
Classifier: License :: OSI Approved :: MIT License
Classifier: Natural Language :: English
Classifier: Programming Language :: Python :: 3
Classifier: Programming Language :: Python :: 3.9
Classifier: Programming Language :: Python :: 3.10
Classifier: Programming Language :: Python :: 3.11
Requires-Dist: Flask
Requires-Dist: flask-jwt-extended
Requires-Dist: flask-sqlalchemy
Requires-Dist: flask-marshmallow
Requires-Dist: flask-migrate
Requires-Dist: flask-smorest
Requires-Dist: flask-cors
Requires-Dist: python-dotenv
Requires-Dist: dependency-injector
Requires-Dist: marshmallow
Requires-Dist: marshmallow-sqlalchemy
